agentic_sentinel-0.1.0.dist-info/licenses/LICENSE
sentinel/__init__.py
sentinel/anomaly/__init__.py
sentinel/anomaly/detector.py
sentinel/anomaly/llm_auditor.py
sentinel/anomaly/statistical.py
sentinel/approval/__init__.py
sentinel/approval/base.py
sentinel/approval/terminal.py
sentinel/approval/webhook.py
sentinel/audit/__init__.py
sentinel/audit/logger.py
sentinel/audit/models.py
sentinel/core/__init__.py
sentinel/core/exceptions.py
sentinel/core/wrapper.py
sentinel/dashboard/__init__.py
sentinel/dashboard/__main__.py
sentinel/dashboard/api.py
sentinel/dashboard/app.py
sentinel/dashboard/state.py
sentinel/integrations/__init__.py
sentinel/integrations/langchain.py
sentinel/rules/__init__.py
sentinel/rules/engine.py
agentic_sentinel-0.1.0.dist-info/METADATA
agentic_sentinel-0.1.0.dist-info/WHEEL
agentic_sentinel-0.1.0.dist-info/top_level.txt
agentic_sentinel-0.1.0.dist-info/RECORD
