Metadata-Version: 2.4
Name: agentic-sentinel
Version: 0.1.0
Summary: Agent Governance Layer - Middleware for AI agent action control
Author: Sentinel Team
License: MIT
Project-URL: Homepage, https://github.com/azdhril/Sentinel
Project-URL: Documentation, https://azdhril.github.io/Sentinel
Project-URL: Repository, https://github.com/azdhril/Sentinel
Project-URL: Issues, https://github.com/azdhril/Sentinel/issues
Keywords: ai,agents,governance,security,middleware
Classifier: Development Status :: 3 - Alpha
Classifier: Intended Audience :: Developers
Classifier: License :: OSI Approved :: MIT License
Classifier: Programming Language :: Python :: 3
Classifier: Programming Language :: Python :: 3.11
Classifier: Programming Language :: Python :: 3.12
Classifier: Topic :: Security
Classifier: Topic :: Software Development :: Libraries :: Python Modules
Requires-Python: >=3.11
License-File: LICENSE
Requires-Dist: pydantic>=2.0
Requires-Dist: structlog>=23.0
Requires-Dist: httpx>=0.25
Requires-Dist: python-dotenv>=1.0
Provides-Extra: dev
Requires-Dist: pytest>=7.0; extra == "dev"
Requires-Dist: pytest-asyncio>=0.21; extra == "dev"
Requires-Dist: pytest-cov>=4.0; extra == "dev"
Requires-Dist: pytest-httpx>=0.30; extra == "dev"
Requires-Dist: mypy>=1.0; extra == "dev"
Requires-Dist: ruff>=0.1; extra == "dev"
Provides-Extra: langchain
Requires-Dist: langchain-core>=0.1.0; extra == "langchain"
Provides-Extra: dashboard
Requires-Dist: streamlit>=1.28.0; extra == "dashboard"
Requires-Dist: plotly>=5.18.0; extra == "dashboard"
Requires-Dist: pandas>=2.0.0; extra == "dashboard"
Requires-Dist: fastapi>=0.104.0; extra == "dashboard"
Requires-Dist: uvicorn>=0.24.0; extra == "dashboard"
Dynamic: license-file
